maxwell/__init__.py
maxwell/client/__init__.py
maxwell/client/client.py
maxwell/client/frontend.py
maxwell/client/master.py
maxwell/client/msg_queue.py
maxwell/client/msg_queue_mgr.py
maxwell/client/subscription_mgr.py
maxwell_client-0.11.0.dist-info/METADATA
maxwell_client-0.11.0.dist-info/WHEEL
maxwell_client-0.11.0.dist-info/licenses/LICENSE
maxwell_client-0.11.0.dist-info/RECORD
