Metadata-Version: 2.3
Name: maxwell-client
Version: 0.11.0
Summary: The maxwell client implementation for python.
Project-URL: changelog, https://github.com/maxwell-dev/maxwell-client-python/CHANGELOG.md
Project-URL: repository, https://github.com/maxwell-dev/maxwell-client-python
Author-email: Xu Chaoqian <chaoranxu@gmail.com>
License:                                  Apache License
License-File: LICENSE
Classifier: License :: OSI Approved :: MIT License
Classifier: Operating System :: OS Independent
Classifier: Programming Language :: Python :: 3
Requires-Python: >=3.7
Requires-Dist: aiohttp>=3.9.5
Requires-Dist: maxwell-protocol>=0.8.0
Requires-Dist: maxwell-utils>=0.7.1
Requires-Dist: websockets>=12.0
Provides-Extra: test
Requires-Dist: pytest-asyncio>=0.23.6; extra == 'test'
Requires-Dist: pytest-cov>=4.1.0; extra == 'test'
Requires-Dist: pytest>=8.1.1; extra == 'test'
